{
  "entities": [
    {
      "components": {
        "Animator": {
          "preset": "UNSPECIFIED",
          "sheet": "orc_sheet",
          "state": "Idle"
        },
        "Collider2D": {
          "halfH": 28.0,
          "halfW": 20.0,
          "isTrigger": false,
          "offsetX": 0.0,
          "offsetY": 2.0
        },
        "RigidBody2D": {
          "accelX": 0.0,
          "accelY": 0.0,
          "enableOneWay": true,
          "enableSlopes": true,
          "gravityScale": 1.0,
          "grounded": false,
          "isStatic": true,
          "linearDamping": 0.0,
          "maxFallSpeed": 0.0,
          "maxStepUp": 0.0,
          "oneWayDisableTimer": 0.0,
          "useGravity": false,
          "velX": 0.0,
          "velY": 0.0
        },
        "Script": {
          "name": "GoblinTest"
        },
        "Sprite2D": {
          "layer": 50,
          "material": "goblin_mat",
          "mesh": "quad",
          "sortKey": 95.0,
          "sortOffsetY": 0.0,
          "uvRect": [
            0.0,
            0.8333333134651184,
            0.125,
            0.1666666716337204
          ]
        },
        "Transform2D": {
          "rot": 0.0,
          "sx": 400.0,
          "sy": 400.0,
          "x": 1080.0,
          "y": 95.0
        }
      },
      "name": "Goblin",
      "uuid": "374e64a91050bf303af0fd65b45fff48"
    },
    {
      "components": {
        "Animator": {
          "preset": "UNSPECIFIED",
          "sheet": "soldier_sheet",
          "state": "Idle"
        },
        "Collider2D": {
          "halfH": 28.0,
          "halfW": 16.0,
          "isTrigger": false,
          "offsetX": 0.0,
          "offsetY": 2.0
        },
        "RigidBody2D": {
          "accelX": 0.0,
          "accelY": 0.0,
          "enableOneWay": true,
          "enableSlopes": true,
          "gravityScale": 1.0,
          "grounded": false,
          "isStatic": true,
          "linearDamping": 0.0,
          "maxFallSpeed": -2200.0,
          "maxStepUp": 22.399999618530273,
          "oneWayDisableTimer": 0.0,
          "useGravity": false,
          "velX": -520.0,
          "velY": 0.0
        },
        "Script": {
          "name": "PlayerController"
        },
        "Sprite2D": {
          "layer": 50,
          "material": "soldier_mat",
          "mesh": "quad",
          "sortKey": 95.0,
          "sortOffsetY": 0.0,
          "uvRect": [
            0.7777777910232544,
            0.7142857313156128,
            0.1111111119389534,
            0.1428571492433548
          ]
        },
        "Transform2D": {
          "rot": 0.0,
          "sx": 400.0,
          "sy": 400.0,
          "x": 563.184326171875,
          "y": 90.0
        }
      },
      "name": "Player",
      "uuid": "928936b76b5f8000505b542b81663b4c"
    }
  ],
  "tilemap": "assets/maps/test_map.json",
  "version": 1
}